hexgraphics/__init__.py
hexgraphics/codec.py
hexgraphics/constants.py
hexgraphics-0.3.2.dist-info/licenses/LICENSE
hexgraphics-0.3.2.dist-info/METADATA
hexgraphics-0.3.2.dist-info/WHEEL
hexgraphics-0.3.2.dist-info/top_level.txt
hexgraphics-0.3.2.dist-info/RECORD
