Metadata-Version: 2.4
Name: hexgraphics
Version: 0.3.2
Summary: aka 0xg
Author: noobiezt0
License-Expression: MIT
Project-URL: Source, https://github.com/noobiezt0/0xg
Classifier: Programming Language :: Python :: 3
Classifier: Operating System :: OS Independent
License-File: LICENSE
Dynamic: license-file
